Metadata-Version: 2.4
Name: fluent_db
Version: 0.3.0
Summary: Fluent DB is a Python library that provides a fluent, chainable interface for building and executing SQL queries—similar to Laravel's ORM. It supports elegant query construction, dynamic table creation, and intuitive data manipulation with a focus on clean, expressive code.
Author-email: Chetan Sharma <chetan.sharma.159116@gmail.com>
License: MIT
Project-URL: Homepage, https://github.com/chetan-sharma-developer/fluent_db
Classifier: Programming Language :: Python :: 3
Classifier: License :: OSI Approved :: MIT License
Classifier: Operating System :: OS Independent
Requires-Python: >=3.6
License-File: LICENSE.md
Dynamic: license-file
